[
  {
    "id": "perf-401810617-4278067",
    "type": "player_performance",
    "timestamp": 1770683400000,
    "sport": "nba",
    "data": {
      "playerName": "Nic Claxton",
      "playerImageUrl": "https://a.espncdn.com/i/headshots/nba/players/full/4278067.png",
      "teamAbbreviation": "BKN",
      "teamLogo": "https://a.espncdn.com/i/teamlogos/nba/500/bkn.png",
      "sport": "nba",
      "stats": {
        "MIN": 32,
        "PTS": 28,
        "FG": 12,
        "3PT": 1,
        "FT": 3,
        "REB": 10,
        "AST": 4,
        "TO": 1,
        "STL": 1,
        "BLK": 0,
        "OREB": 3,
        "DREB": 7,
        "PF": 4,
        "+/-": 17
      },
      "headline": "28 PTS | 10 REB | 4 AST",
      "gameId": "401810617",
      "opponentAbbreviation": "CHI",
      "gameDate": "2026-02-10",
      "isWin": true
    }
  },
  {
    "id": "perf-401810617-5279130",
    "type": "player_performance",
    "timestamp": 1770683400000,
    "sport": "nba",
    "data": {
      "playerName": "Nolan Traore",
      "playerImageUrl": "https://a.espncdn.com/i/headshots/nba/players/full/5279130.png",
      "teamAbbreviation": "BKN",
      "teamLogo": "https://a.espncdn.com/i/teamlogos/nba/500/bkn.png",
      "sport": "nba",
      "stats": {
        "MIN": 32,
        "PTS": 13,
        "FG": 5,
        "3PT": 0,
        "FT": 3,
        "REB": 3,
        "AST": 13,
        "TO": 3,
        "STL": 1,
        "BLK": 1,
        "OREB": 1,
        "DREB": 2,
        "PF": 4,
        "+/-": 17
      },
      "headline": "13 PTS | 3 REB | 13 AST",
      "gameId": "401810617",
      "opponentAbbreviation": "CHI",
      "gameDate": "2026-02-10",
      "isWin": true
    }
  }
]